CHANGELOG.md
bencher/__init__.py
bencher/bench_cfg.py
bencher/bench_plot_server.py
bencher/bench_report.py
bencher/bench_runner.py
bencher/bencher.py
bencher/caching.py
bencher/class_enum.py
bencher/factories.py
bencher/flask_server.py
bencher/job.py
bencher/optuna_conversions.py
bencher/py.typed
bencher/result_collector.py
bencher/sample_order.py
bencher/sweep_executor.py
bencher/utils.py
bencher/utils_rerun.py
bencher/video_writer.py
bencher/worker_job.py
bencher/worker_manager.py
bencher/example/__init__.py
bencher/example/benchmark_data.py
bencher/example/example_all.py
bencher/example/example_benchrunner.py
bencher/example/example_bool_result.py
bencher/example/example_cat2_scatter_jitter.py
bencher/example/example_categorical.py
bencher/example/example_composable_container2.py
bencher/example/example_composable_container_image.py
bencher/example/example_composable_container_video.py
bencher/example/example_consts.py
bencher/example/example_custom_sweep.py
bencher/example/example_custom_sweep2.py
bencher/example/example_dataframe.py
bencher/example/example_docs.py
bencher/example/example_filepath.py
bencher/example/example_float3D.py
bencher/example/example_float_cat.py
bencher/example/example_floats.py
bencher/example/example_floats2D.py
bencher/example/example_holosweep.py
bencher/example/example_holosweep_objects.py
bencher/example/example_holosweep_tap.py
bencher/example/example_image.py
bencher/example/example_image1.py
bencher/example/example_image_vid.py
bencher/example/example_levels.py
bencher/example/example_pareto.py
bencher/example/example_publish.py
bencher/example/example_rerun.py
bencher/example/example_rerun2.py
bencher/example/example_sample_cache.py
bencher/example/example_sample_cache_context.py
bencher/example/example_simple.py
bencher/example/example_simple_bool.py
bencher/example/example_simple_cat.py
bencher/example/example_simple_float.py
bencher/example/example_simple_float2d.py
bencher/example/example_strings.py
holobench-1.60.0.dist-info/METADATA
holobench-1.60.0.dist-info/WHEEL
holobench-1.60.0.dist-info/licenses/LICENSE
holobench-1.60.0.dist-info/RECORD
