Metadata-Version: 2.4
Name: holobench
Version: 1.60.0
Summary: A package for benchmarking the performance of arbitrary functions
Project-URL: Repository, https://github.com/blooop/bencher
Project-URL: Home, https://github.com/blooop/bencher
Project-URL: Documentation, https://bencher.readthedocs.io/en/latest/
Author-email: Austin Gregg-Smith <blooop@gmail.com>
License-Expression: MIT
License-File: LICENSE
Requires-Python: <3.14,>=3.10
Requires-Dist: diskcache<=5.6.3,>=5.6
Requires-Dist: holoviews<=1.22.1,>=1.15
Requires-Dist: hvplot<=0.12.2,>=0.12.0
Requires-Dist: moviepy<=2.2.1,>=2.1.2
Requires-Dist: numpy<=2.4.1,>=1.0
Requires-Dist: optuna<=4.7.0,>=3.2
Requires-Dist: pandas<=3.0.0,>=2.0
Requires-Dist: panel<=1.8.5,>=1.3.6
Requires-Dist: param<=2.3.1,>=1.13.0
Requires-Dist: plotly<=6.5.2,>=5.15
Requires-Dist: scikit-learn<=1.7.2,>=1.2
Requires-Dist: strenum<=0.4.15,>=0.4.0
Requires-Dist: xarray<=2025.6.1,>=2023.7
Provides-Extra: rerun
Requires-Dist: flask; extra == 'rerun'
Requires-Dist: flask-cors; extra == 'rerun'
Requires-Dist: rerun-notebook; extra == 'rerun'
Requires-Dist: rerun-sdk>=0.24.0; extra == 'rerun'
Provides-Extra: test
Requires-Dist: coverage<=7.13.1,>=7.5.4; extra == 'test'
Requires-Dist: hypothesis<=6.150.3,>=6.104.2; extra == 'test'
Requires-Dist: ipykernel; extra == 'test'
Requires-Dist: jupyter-bokeh; extra == 'test'
Requires-Dist: nbformat; extra == 'test'
Requires-Dist: pip; extra == 'test'
Requires-Dist: prek<0.4.0,>=0.2.28; extra == 'test'
Requires-Dist: pylint<=4.0.4,>=3.2.5; extra == 'test'
Requires-Dist: pytest-cov<=7.0.0,>=4.1; extra == 'test'
Requires-Dist: pytest<=9.0.2,>=7.4; extra == 'test'
Requires-Dist: ruff<=0.14.14,>=0.5.0; extra == 'test'
Requires-Dist: ty<=0.0.13,>=0.0.13; extra == 'test'
